LICENSE
MANIFEST.in
README.md
pyproject.toml
setup.py
tox.ini
src/Pegasus/__init__.py
src/Pegasus/braindump.py
src/Pegasus/json.py
src/Pegasus/yaml.py
src/Pegasus/client/__init__.py
src/Pegasus/client/_client.py
src/Pegasus/client/condor.py
src/Pegasus/client/status.py
src/pegasus_wms.common.egg-info/PKG-INFO
src/pegasus_wms.common.egg-info/SOURCES.txt
src/pegasus_wms.common.egg-info/dependency_links.txt
src/pegasus_wms.common.egg-info/not-zip-safe
src/pegasus_wms.common.egg-info/requires.txt
src/pegasus_wms.common.egg-info/top_level.txt
test/test_braindump.py
test/test_condor.py
test/test_json.py
test/test_status.py
test/test_yaml.py
test/client/test_client.py
test/status_sample_files/sample1/braindump.yml
test/status_sample_files/sample1/sample_1_success.dag.dagman.out
test/status_sample_files/sample1_hr/sample1_hr_success.dag.dagman.out
test/status_sample_files/sample1_hr/sub_workflows/inner/inner.dag.dagman.out
test/status_sample_files/sample1_hr/sub_workflows/sleep_subworkflow/sleep-wf-0.dag.dagman.out
test/status_sample_files/sample2/sample_2_held.dag.dagman.out
test/status_sample_files/sample2_hr/sample2_hr_failure.dag.dagman.out
test/status_sample_files/sample2_hr/sub_workflows/inner/inner.dag.dagman.out
test/status_sample_files/sample3/sample_3_failure.dag.dagman.out
test/status_sample_files/sample4/sample_4_removed.dag.dagman.out
test/status_sample_files/sample5/sample_5_failed_with_no_progress_lines.dag.dagman.out