Metadata-Version: 2.1
Name: pegasus-wms.common
Version: 5.1.1
Summary: Pegasus Workflow Management System Python Commons
Home-page: http://pegasus.isi.edu
Author: Pegasus Team
Author-email: pegasus@isi.edu
License: Apache2
Project-URL: Documentation, https://pegasus.isi.edu/documentation/
Project-URL: Changes, https://pegasus.isi.edu/blog/?category_name=Release
Project-URL: Source Code, https://github.com/pegasus-isi/pegasus
Project-URL: Issue Tracker, https://github.com/pegasus-isi/pegasus/issues
Keywords: scientific workflows
Platform: UNKNOWN
Classifier: Development Status :: 5 - Production/Stable
Classifier: Intended Audience :: Developers
Classifier: Intended Audience :: Science/Research
Classifier: Operating System :: Unix
Classifier: Programming Language :: Python
Classifier: Programming Language :: Python :: 3
Classifier: Programming Language :: Python :: 3 :: Only
Classifier: Programming Language :: Python :: 3.6
Classifier: Programming Language :: Python :: 3.7
Classifier: Programming Language :: Python :: 3.8
Classifier: Programming Language :: Python :: 3.9
Classifier: Programming Language :: Python :: 3.10
Classifier: Programming Language :: Python :: 3.11
Classifier: Programming Language :: Python :: 3.12
Classifier: Programming Language :: Python :: 3.13
Classifier: Topic :: Scientific/Engineering
Classifier: Topic :: Utilities
Classifier: License :: OSI Approved :: Apache Software License
Requires-Python: >=3.6
License-File: LICENSE
